qeijo/__init__.py
qeijo/pw.py
qeijo-0.1.dist-info/METADATA
qeijo-0.1.dist-info/WHEEL
qeijo-0.1.dist-info/top_level.txt
qeijo-0.1.dist-info/RECORD
