Metadata-Version: 2.1
Name: qeijo
Version: 0.1
Summary: Lightweight library to easily launch ab initio calculations with Quantum Espresso.
Home-page: https://github.com/rgaveiga/qeijo
Author: Roberto Gomes de Aguiar Veiga
License: UNKNOWN
Platform: UNKNOWN
Requires: subprocess
Requires: io
Requires: os
Requires: shlex
Requires: exceptions
